lit_wsl/__about__.py
lit_wsl/__init__.py
lit_wsl/callbacks/gpu_monitoring.py
lit_wsl/cli.py
lit_wsl/data/datamodule.py
lit_wsl/data/dummy.py
lit_wsl/models/checkpoint.py
lit_wsl/models/intermediate_layer_getter.py
lit_wsl/models/weight_mapper.py
lit_wsl/models/weight_renamer.py
lit_wsl/py.typed
lit_wsl/testing/lightning_tester.py
lit_wsl/training/stages.py
lit_wsl/utils/logger.py
lit_wsl-0.2.0.dist-info/METADATA
lit_wsl-0.2.0.dist-info/WHEEL
lit_wsl-0.2.0.dist-info/entry_points.txt
lit_wsl-0.2.0.dist-info/licenses/LICENSE
lit_wsl-0.2.0.dist-info/RECORD
