Metadata-Version: 2.4
Name: lit-wsl
Version: 0.2.0
Summary: My personal library of reusable Lightning components
License: MIT
License-File: LICENSE
Keywords: lit-wsl
Author: twsl
Author-email: 45483159+twsl@users.noreply.github.com
Requires-Python: >=3.11
Classifier: License :: OSI Approved :: MIT License
Classifier: Programming Language :: Python :: 3
Classifier: Programming Language :: Python :: 3.11
Classifier: Programming Language :: Python :: 3.12
Classifier: Programming Language :: Python :: 3.13
Classifier: Programming Language :: Python :: 3.14
Requires-Dist: lightning (>=2.6.0,<3.0.0)
Project-URL: Documentation, https://twsl.github.io/lit-wsl/
Project-URL: Homepage, https://twsl.github.io/lit-wsl/
Project-URL: Repository, https://github.com/twsl/lit-wsl
